pyscli/__init__.py
pyscli/__main__.py
PySCli-1.0.dist-info/LICENSE.txt
PySCli-1.0.dist-info/METADATA
PySCli-1.0.dist-info/WHEEL
PySCli-1.0.dist-info/top_level.txt
PySCli-1.0.dist-info/RECORD
