Metadata-Version: 2.1
Name: PySCli
Version: 1.0
Summary: A Module to Get User Terminal Commands...
Home-page: https://github.com/sancho1952007/PySCli/
Author: Sancho Godinho
License: UNKNOWN
Project-URL: Bug Tracker, https://github.com/sancho1952007/PySCli/issues
Keywords: cli()
Platform: UNKNOWN
